Workbook
Name Slicer_Region: #N/A
Name Slicer_Years: #N/A

Sheet Data
B2: Retailer Dataset
B4: Retailer | C4: Retailer ID | D4: Invoice Date | E4: Region | F4: State | G4: City | H4: Beverage Brand | I4: Price per Unit | J4: Units Sold | K4: Total Sales | L4: Operating Profit | M4: Operating Margin
B5: BevCo | C5: 1185732 | D5: 44562 | E5: Northeast | F5: New York | G5: New York | H5: Coca-Cola | I5: 0.5 | J5: 12000 | K5: 6000 | L5: 3000 | M5: 0.5
B6: BevCo | C6: 1185732 | D6: 44563 | E6: Northeast | F6: New York | G6: New York | H6: Diet Coke | I6: 0.5 | J6: 10000 | K6: 5000 | L6: 1500 | M6: 0.3
B7: BevCo | C7: 1185732 | D7: 44564 | E7: Northeast | F7: New York | G7: New York | H7: Sprite | I7: 0.4 | J7: 10000 | K7: 4000 | L7: 1400 | M7: 0.35
B8: BevCo | C8: 1185732 | D8: 44565 | E8: Northeast | F8: New York | G8: New York | H8: Fanta | I8: 0.45 | J8: 8500 | K8: 3825 | L8: 1338.75 | M8: 0.35
B9: BevCo | C9: 1185732 | D9: 44566 | E9: Northeast | F9: New York | G9: New York | H9: Powerade | I9: 0.6 | J9: 9000 | K9: 5400 | L9: 1620 | M9: 0.3
B10: BevCo | C10: 1185732 | D10: 44567 | E10: Northeast | F10: New York | G10: New York | H10: Dasani Water | I10: 0.5 | J10: 10000 | K10: 5000 | L10: 1250 | M10: 0.25
B11: BevCo | C11: 1185732 | D11: 44568 | E11: Northeast | F11: New York | G11: New York | H11: Coca-Cola | I11: 0.5 | J11: 12500 | K11: 6250 | L11: 3125 | M11: 0.5
B12: BevCo | C12: 1185732 | D12: 44569 | E12: Northeast | F12: New York | G12: New York | H12: Diet Coke | I12: 0.5 | J12: 9000 | K12: 4500 | L12: 1350 | M12: 0.3
B13: BevCo | C13: 1185732 | D13: 44582 | E13: Northeast | F13: New York | G13: New York | H13: Sprite | I13: 0.4 | J13: 9500 | K13: 3800 | L13: 1330 | M13: 0.35
B14: BevCo | C14: 1185732 | D14: 44583 | E14: Northeast | F14: New York | G14: New York | H14: Fanta | I14: 0.45 | J14: 8250 | K14: 3712.5 | L14: 1299.375 | M14: 0.35
B15: BevCo | C15: 1185732 | D15: 44584 | E15: Northeast | F15: New York | G15: New York | H15: Powerade | I15: 0.6 | J15: 9000 | K15: 5400 | L15: 1620 | M15: 0.3
B16: BevCo | C16: 1185732 | D16: 44585 | E16: Northeast | F16: New York | G16: New York | H16: Dasani Water | I16: 0.5 | J16: 10000 | K16: 5000 | L16: 1250 | M16: 0.25
... B9652: BevCo | C9652: 1185732 | D9652: 44979 | E9652: Northeast | F9652: New Hampshire | G9652: Manchester | H9652: Sprite | I9652: 0.29 | J9652: 830 | K9652: 240.7 | L9652: 64.989 | M9652: 0.27

Sheet Analyze
A1: Sum of Total Sales | B1: Sum of Units Sold | C1: Average of Price per Unit | D1: Sum of Operating Profit
A2: 12016665 | B2: 24788610 | C2: 0.45216625 | D2: 4722496.8
A4: Sum of Total Sales | B4: Column Labels
A5: Row Labels | B5: 2022 | C5: 2023 | D5: Grand Total
A6: Coca-Cola | B6: 499102 | C6: 2268974.9 | D6: 2768076.9
A7: Dasani Water | B7: 469270.7 | C7: 1917827.8 | D7: 2387098.5
A8: Diet Coke | B8: 423758.7 | C8: 1633959.3 | D8: 2057718
A9: Fanta | B9: 315489.2 | C9: 1116062.9 | D9: 1431552.1
A10: Powerade | B10: 349533.9 | C10: 1302529.3 | D10: 1652063.2
A11: Sprite | B11: 366578 | C11: 1353578.3 | D11: 1720156.3
A12: Grand Total | B12: 2423732.5 | C12: 9592932.5 | D12: 12016665
A14: Sum of Total Sales | B14: Column Labels
A15: Row Labels | B15: 2022 | C15: 2023 | D15: Grand Total
A16: Amazon | B16: 276210 | C16: 1009698.7 | D16: 1285908.7
A17: BevCo | B17: 466788 | C17: 2327606.5 | D17: 2794394.5
A18: FizzyCo | B18: 161210.1 | C18: 2262827.1 | D18: 2424037.2
A19: Target | B19: 9250.3 | C19: 1341995 | D19: 1351245.3
A20: Walmart | B20: 339912.5 | C20: 580211 | D20: 920123.5
A21: West Soda | B21: 1170361.6 | C21: 2070594.2 | D21: 3240955.8
A22: Grand Total | B22: 2423732.5 | C22: 9592932.5 | D22: 12016665
A25: Years | B25: Quarters | C25: Sum of Total Sales | D25: Average of Operating Margin
A26: 2022 | B26: Qtr1 | C26: 692776.1 | D26: 0.40174684 | E26: =A26 -> 2022 | F26: =B26 -> Qtr1 | G26: =C26 -> 692776.1 | H26: =D26 -> 0.40174684
B27: Qtr2 | C27: 644203.9 | D27: 0.4 | F27: =B27 -> Qtr2 | G27: =C27 -> 644203.9 | H27: =D27 -> 0.4
B28: Qtr3 | C28: 719170.4 | D28: 0.41026549 | F28: =B28 -> Qtr3 | G28: =C28 -> 719170.4 | H28: =D28 -> 0.41026549
B29: Qtr4 | C29: 367582.1 | D29: 0.40243816 | F29: =B29 -> Qtr4 | G29: =C29 -> 367582.1 | H29: =D29 -> 0.40243816
A30: 2023 | B30: Qtr1 | C30: 1877584.3 | D30: 0.41657045 | E30: =A30 -> 2023 | F30: =B30 -> Qtr1 | G30: =C30 -> 1877584.3 | H30: =D30 -> 0.41657045
B31: Qtr2 | C31: 2379424.8 | D31: 0.42755819 | F31: =B31 -> Qtr2 | G31: =C31 -> 2379424.8 | H31: =D31 -> 0.42755819
B32: Qtr3 | C32: 2805752.5 | D32: 0.4347017 | F32: =B32 -> Qtr3 | G32: =C32 -> 2805752.5 | H32: =D32 -> 0.4347017
B33: Qtr4 | C33: 2530170.9 | D33: 0.42483933 | F33: =B33 -> Qtr4 | G33: =C33 -> 2530170.9 | H33: =D33 -> 0.42483933
A34: Grand Total | C34: 12016665 | D34: 0.42299129

Sheet Dashboard
C10: Sales By Beverage Brand | H10: Sales By Beverage Brand
C11: Brand | D11: Sales 2022 | E11: Sales 2023 | F11: Varience | H11: Retailers | I11: Sales 2022 | J11: Sales 2023 | K11: Varience
C12: =Analyze!A6 -> Coca-Cola | D12: =Analyze!B6 -> 499102 | E12: =Analyze!C6 -> 2268974.9 | F12: =E12-D12 -> 1769872.9 | H12: =Analyze!A16 -> Amazon | I12: =Analyze!B16 -> 276210 | J12: =Analyze!C16 -> 1009698.7 | K12: =Analyze!D16 -> 1285908.7
C13: =Analyze!A7 -> Dasani Water | D13: =Analyze!B7 -> 469270.7 | E13: =Analyze!C7 -> 1917827.8 | F13: =E13-D13 -> 1448557.1 | H13: =Analyze!A17 -> BevCo | I13: =Analyze!B17 -> 466788 | J13: =Analyze!C17 -> 2327606.5 | K13: =Analyze!D17 -> 2794394.5
C14: =Analyze!A8 -> Diet Coke | D14: =Analyze!B8 -> 423758.7 | E14: =Analyze!C8 -> 1633959.3 | F14: =E14-D14 -> 1210200.6 | H14: =Analyze!A18 -> FizzyCo | I14: =Analyze!B18 -> 161210.1 | J14: =Analyze!C18 -> 2262827.1 | K14: =Analyze!D18 -> 2424037.2
C15: =Analyze!A9 -> Fanta | D15: =Analyze!B9 -> 315489.2 | E15: =Analyze!C9 -> 1116062.9 | F15: =E15-D15 -> 800573.7 | H15: =Analyze!A19 -> Target | I15: =Analyze!B19 -> 9250.3 | J15: =Analyze!C19 -> 1341995 | K15: =Analyze!D19 -> 1351245.3
C16: =Analyze!A10 -> Powerade | D16: =Analyze!B10 -> 349533.9 | E16: =Analyze!C10 -> 1302529.3 | F16: =E16-D16 -> 952995.4 | H16: =Analyze!A20 -> Walmart | I16: =Analyze!B20 -> 339912.5 | J16: =Analyze!C20 -> 580211 | K16: =Analyze!D20 -> 920123.5
C17: =Analyze!A11 -> Sprite | D17: =Analyze!B11 -> 366578 | E17: =Analyze!C11 -> 1353578.3 | F17: =E17-D17 -> 987000.3 | H17: =Analyze!A21 -> West Soda | I17: =Analyze!B21 -> 1170361.6 | J17: =Analyze!C21 -> 2070594.2 | K17: =Analyze!D21 -> 3240955.8
C18: Total | D18: =SUM(D12:D17) -> 2423732.5 | E18: =SUM(E12:E17) -> 9592932.5 | F18: =SUM(F12:F17) -> 7169200 | H18: Total | I18: =SUM(I12:I17) -> 2423732.5 | J18: =SUM(J12:J17) -> 9592932.5 | K18: =SUM(K12:K17) -> 12016665
A19: Last Update Jan 2024
C20: Sales and Operating Profit Margin By Quarter
